kishu/__init__.py
kishu/cli.py
kishu/commands.py
kishu/diff.py
kishu/exceptions.py
kishu/jupyterint.py
kishu/logging.py
kishu/notebook_id.py
kishu/py.typed
kishu/jupyter/__init__.py
kishu/jupyter/namespace.py
kishu/jupyter/runtime.py
kishu/planning/__init__.py
kishu/planning/ahg.py
kishu/planning/hash_visitor.py
kishu/planning/idgraph.py
kishu/planning/idgraph_visitor.py
kishu/planning/object_state.py
kishu/planning/optimizer.py
kishu/planning/plan.py
kishu/planning/planner.py
kishu/planning/profiler.py
kishu/planning/variable_version_tracker.py
kishu/planning/visitor.py
kishu/storage/__init__.py
kishu/storage/branch.py
kishu/storage/checkpoint.py
kishu/storage/commit.py
kishu/storage/commit_graph.py
kishu/storage/config.py
kishu/storage/connection.py
kishu/storage/disk_ahg.py
kishu/storage/path.py
kishu/storage/tag.py
kishu/storage/variable_version.py
kishu-0.3.4.dist-info/METADATA
kishu-0.3.4.dist-info/WHEEL
kishu-0.3.4.dist-info/entry_points.txt
kishu-0.3.4.dist-info/top_level.txt
kishu-0.3.4.dist-info/RECORD
