Metadata-Version: 2.1
Name: kishu
Version: 0.3.4
Summary: Intelligent Python Checkpointing
Author-email: Yongjoo Park <yongjoo@g.illinois.edu>, Supawit Chockchowwat <supawit2@illinois.edu>, Zhaoheng Li <zl20@illinois.edu>
License: Apache-2.0
Project-URL: repository, https://github.com/illinoisdata/kishu
Keywords: kishu,elastic,dart,python,jupyter,notebook,server,lab,cli,web,gui,extension
Classifier: Framework :: Jupyter
Classifier: Framework :: Jupyter :: JupyterLab
Classifier: Framework :: Jupyter :: JupyterLab :: 4
Classifier: License :: OSI Approved :: Apache Software License
Classifier: Programming Language :: Python
Classifier: Programming Language :: Python :: 3
Classifier: Programming Language :: Python :: 3.8
Classifier: Programming Language :: Python :: 3.9
Classifier: Programming Language :: Python :: 3.10
Classifier: Programming Language :: Python :: 3.11
Requires-Python: >=3.8
Requires-Dist: dataclasses
Requires-Dist: dataclasses-json
Requires-Dist: dill
Requires-Dist: ipykernel
Requires-Dist: ipylab
Requires-Dist: jupyter-ui-poll <=1.0.0
Requires-Dist: loguru
Requires-Dist: nbconvert
Requires-Dist: nbformat
Requires-Dist: networkx
Requires-Dist: psutil
Requires-Dist: requests
Requires-Dist: typing
Requires-Dist: flask
Requires-Dist: rich
Requires-Dist: typer
Requires-Dist: Flask-CORS
Requires-Dist: numpy
Requires-Dist: pandas
Requires-Dist: shortuuid
Requires-Dist: xxhash
Provides-Extra: dev
Requires-Dist: black ; extra == 'dev'
Requires-Dist: flake8 ; extra == 'dev'
Requires-Dist: isort ; extra == 'dev'
Requires-Dist: mypy ; extra == 'dev'
Requires-Dist: pytest ; extra == 'dev'
Requires-Dist: pytest-cov ; extra == 'dev'
Requires-Dist: pytest-benchmark ; extra == 'dev'
Requires-Dist: pytest-xdist ; extra == 'dev'
Requires-Dist: matplotlib ; extra == 'dev'
Requires-Dist: numpy ; extra == 'dev'
Requires-Dist: scikit-learn ; extra == 'dev'
Requires-Dist: seaborn ; extra == 'dev'
Requires-Dist: textblob ; extra == 'dev'
Requires-Dist: pandas ; extra == 'dev'
Requires-Dist: pylatexenc ; extra == 'dev'
Requires-Dist: websocket-client ; extra == 'dev'
Requires-Dist: requests ; extra == 'dev'
Requires-Dist: types-requests ; extra == 'dev'
Requires-Dist: jupyter ; extra == 'dev'
